{
	"definitionVersion": "0.201.3",
	"build": {
		"latest": true,
		"rootDistro": "debian",
		"tags": [
			"miniconda:${VERSION}-3"
		]
	},
	"dependencies": {
		"image": "miniconda3:latest",
		"imageLink": "https://hub.docker.com/r/continuumio/miniconda3",
		"debian": [
			"yarn"
		],
		"git": {
			"Oh My Zsh!": "/root/.oh-my-zsh",
			"nvm": "/usr/local/share/nvm"
		},
		"pipx": [
			"pylint",
			"flake8",
			"autopep8",
			"black",
			"yapf",
			"mypy",
			"pydocstyle",
			"pycodestyle",
			"bandit",
			"virtualenv",
			"pipx"
		]
	}
}